{
  "timestamp": "2025-06-28T23:17:00.680Z",
  "worldDimensions": {
    "width": 55,
    "height": 41.25
  },
  "species": [
    {
      "id": "gpu_species_0",
      "name": "GPU Species 1",
      "pointCount": 10000,
      "params": {
        "mu_k": 6.003318112561251,
        "sigma_k": 1.395170337963014,
        "w_k": 0.03732875382887859,
        "mu_g": 0.6661106661616153,
        "sigma_g": 0.07562018525446845,
        "c_rep": 2.23911992195814,
        "kernel_k_type": "mexican_hat",
        "kernel_g_type": "mexican_hat"
      },
      "color": "#00ff88"
    },
    {
      "id": "gpu_species_1",
      "name": "GPU Species 2",
      "pointCount": 10000,
      "params": {
        "mu_k": 6.620543139353109,
        "sigma_k": 2.6629498962563587,
        "w_k": 0.04993176718229276,
        "mu_g": 0.3735976079421627,
        "sigma_g": 0.2066512932953165,
        "c_rep": 2.691454173933337,
        "kernel_k_type": "sinc",
        "kernel_g_type": "sinc"
      },
      "color": "#4488ff"
    },
    {
      "id": "gpu_species_2",
      "name": "GPU Species 3",
      "pointCount": 10000,
      "params": {
        "mu_k": 2.7911809141732835,
        "sigma_k": 0.6365844342369238,
        "w_k": 0.1174637492737882,
        "mu_g": 0.5877053583940386,
        "sigma_g": 0.3045592500986745,
        "c_rep": 0.31729640554524596,
        "kernel_k_type": "polynomial",
        "kernel_g_type": "mexican_hat"
      },
      "color": "#ff4488"
    }
  ]
}